starfishX/AD.py
starfishX/DividendDiscountModel.py
starfishX/DuPontROE.py
starfishX/EYG.py
starfishX/Elder.py
starfishX/InterestBearingDebt.py
starfishX/Ke.py
starfishX/ShareholdersNow.py
starfishX/__init__.py
starfishX/checkServices.py
starfishX/config.py
starfishX/dashFn.py
starfishX/depreciationAndAmortisation.py
starfishX/findMarketCap.py
starfishX/findSector.py
starfishX/getDW.py
starfishX/getEVEBITDA.py
starfishX/getFundamentalInSector.py
starfishX/getProfitAbility.py
starfishX/getWarrant.py
starfishX/greek.py
starfishX/helpers.py
starfishX/holidayMarket.py
starfishX/incomestatement.py
starfishX/indexMarket.py
starfishX/indicator.py
starfishX/ipoStat.py
starfishX/listSecurities.py
starfishX/loadHistData_v2.py
starfishX/marketValueDaily.py
starfishX/marketview.py
starfishX/moc.py
starfishX/morningstarGetfn.py
starfishX/news_api.py
starfishX/npl_fn.py
starfishX/nvdr.py
starfishX/openInterest.py
starfishX/risk_kit.py
starfishX/sentimentAnalysis.py
starfishX/shortsale.py
starfishX/squarify.py
starfishX/starfishXfn.py
starfishX/utilHelpers.py
starfishX/utility.py
starfishX/markminervini/__init__.py
starfishX/markminervini/trendtemplate.py
starfishX/peterlynch/__init__.py
starfishX/peterlynch/balancesheet.py
starfishX/peterlynch/condition.py
starfishX/peterlynch/fcf.py
starfishX/peterlynch/iaa.py
starfishX/peterlynch/industrial.py
starfishX/peterlynch/longtermdebt.py
starfishX/peterlynch/pehistory.py
starfishX/peterlynch/peproxy.py
starfishX/peterlynch/r59.py
starfishX/peterlynch/shareholders.py
starfishX/peterlynch/sixclass.py
starfishX/peterlynch/strategy.py
starfishX/peterlynch/sumofthepart.py
starfishX/volatility/__init__.py
starfishX/volatility/typevol.py
starfishX/volatility/vol.py
starfishX-0.155556.dist-info/METADATA
starfishX-0.155556.dist-info/WHEEL
starfishX-0.155556.dist-info/top_level.txt
starfishX-0.155556.dist-info/RECORD
