Metadata-Version: 2.1
Name: starfishX
Version: 0.155556
Summary: Get data of stock exchange thailand (SET)
Home-page: https://github.com/tapattan/starfishX
Author: nattapat attiratanasunthron
Author-email: tapattan@gmail.com
Keywords: starfishx,finance,การลงทุน,หุ้น,peterlynch
Requires-Dist: requests
Requires-Dist: beautifulsoup4
Requires-Dist: urllib3
Requires-Dist: pyqt5
Requires-Dist: pandas
Requires-Dist: html5lib
Requires-Dist: ffn
Requires-Dist: tqdm
Requires-Dist: seaborn
Requires-Dist: scipy
Requires-Dist: sklearn
Requires-Dist: squarify
Requires-Dist: selenium
Requires-Dist: pythainlp
Requires-Dist: mplfinance
Requires-Dist: tvdatafeed
